{
  "timeTests": {
    "3DwRTQjNCPA72oMC7D2x": {
      "localTimeWhenWriting": "2025-06-06T19:13:09.548Z",
      "createdAt": {
        "_seconds": 1749237190,
        "_nanoseconds": 178000000
      }
    },
    "tzXUVbcDxe9OYsAH4xZP": {
      "localTimeWhenWriting": "2025-06-06T19:13:09.552Z",
      "createdAt": {
        "_seconds": 1749237190,
        "_nanoseconds": 492000000
      }
    }
  },
  "trips": {
    "9L1OvDNuocdbwtst0YJV": {
      "name": "OOTY",
      "destination": "Bengaluru,Ooty,Coorg,Mysore",
      "startDate": {
        "_seconds": 1750789800,
        "_nanoseconds": 0
      },
      "endDate": {
        "_seconds": 1751221800,
        "_nanoseconds": 0
      },
      "description": "",
      "coverPhotoURL": "https://placehold.co/600x400.png?text=OOTY",
      "dataAiHint": "bengaluru travel",
      "baseCurrency": "INR",
      "ownerId": "ZDif3dTZDmfNOcgvqFoVO1xEizi2",
      "members": [
        "ZDif3dTZDmfNOcgvqFoVO1xEizi2"
      ],
      "createdAt": {
        "_seconds": 1750750181,
        "_nanoseconds": 162000000
      }
    },
    "DZMsNgJ8AYnDMvfGXbT1": {
      "destination": "Darjeeling",
      "startDate": {
        "_seconds": 1751049000,
        "_nanoseconds": 0
      },
      "endDate": {
        "_seconds": 1751308200,
        "_nanoseconds": 0
      },
      "description": "We will rock Darjeeling. Siiiiiiiiuuuuuuuuuuuuuuuu!!!!!!!!!",
      "dataAiHint": "darjeeling travel",
      "baseCurrency": "INR",
      "ownerId": "nFwfgL28iJT5nCDVPaPAHnya7jg2",
      "createdAt": {
        "_seconds": 1750777500,
        "_nanoseconds": 403000000
      },
      "name": "Darjeeling Jomjomat",
      "coverPhotoURL": "https://unsplash.com/photos/aerial-view-of-city-near-mountain-during-daytime-1I07SYGwuys",
      "members": [
        "nFwfgL28iJT5nCDVPaPAHnya7jg2",
        "h5uHIffYuzML5TW4r6Z3IRy0bC13",
        "0UvIfHXyRkNsyanC3gZyIfcH7s02",
        "2KmSLWs2rzRAUf5gw8hub6ywW9x1",
        "pMHCV5Ps6ASc3dmQJdi5o2ageUD2",
        "OFwktrmtGVaU7eOUVo2BEzgh1Ir2",
        "EswwiypXSlNvwyuhDRQl62r4jRF3",
        "ejvuhdTDUaNlunDreHiw6DSfZzc2",
        "8gXk0K0IrldaCTvCkMRIcBSqkei1"
      ]
    },
    "GxV66kUfIBOMGhes80Jl": {
      "name": "Hack4Bengal Final Round",
      "destination": "SNU Kolkata",
      "startDate": {
        "_seconds": 1750530600,
        "_nanoseconds": 0
      },
      "endDate": {
        "_seconds": 1750617000,
        "_nanoseconds": 0
      },
      "description": "We are DEV NEXUS PRIME and we will try our best.",
      "coverPhotoURL": "https://placehold.co/600x400.png?text=Hack4Bengal%20Final%20Round",
      "dataAiHint": "snu kolkata travel",
      "baseCurrency": "INR",
      "ownerId": "2KmSLWs2rzRAUf5gw8hub6ywW9x1",
      "createdAt": {
        "_seconds": 1750534371,
        "_nanoseconds": 868000000
      },
      "members": [
        "2KmSLWs2rzRAUf5gw8hub6ywW9x1",
        "nFwfgL28iJT5nCDVPaPAHnya7jg2",
        "qz8Mre992HZ2oZzS9fnvrGPZ4sz2",
        "Fzdmgoj5LpYHAweyMfiFSPXghj22"
      ]
    },
    "MV5yasfSPm2iefJbuqMY": {
      "name": "Kenakati ",
      "destination": "Darjeeling ",
      "startDate": {
        "_seconds": 1751308200,
        "_nanoseconds": 0
      },
      "endDate": {
        "_seconds": 1751308200,
        "_nanoseconds": 0
      },
      "description": "",
      "coverPhotoURL": "https://placehold.co/600x400.png?text=Kenakati%20",
      "dataAiHint": "darjeeling travel",
      "baseCurrency": "INR",
      "ownerId": "nFwfgL28iJT5nCDVPaPAHnya7jg2",
      "createdAt": {
        "_seconds": 1751376839,
        "_nanoseconds": 543000000
      },
      "members": [
        "nFwfgL28iJT5nCDVPaPAHnya7jg2",
        "2KmSLWs2rzRAUf5gw8hub6ywW9x1",
        "h5uHIffYuzML5TW4r6Z3IRy0bC13",
        "pMHCV5Ps6ASc3dmQJdi5o2ageUD2",
        "ejvuhdTDUaNlunDreHiw6DSfZzc2",
        "0UvIfHXyRkNsyanC3gZyIfcH7s02"
      ]
    },
    "MtTShwBp8Io6GGtkvtLp": {
      "name": "Testing",
      "destination": "Testing",
      "startDate": {
        "_seconds": 1750789800,
        "_nanoseconds": 0
      },
      "endDate": {
        "_seconds": 1750789800,
        "_nanoseconds": 0
      },
      "description": "",
      "coverPhotoURL": "https://placehold.co/600x400.png?text=Testing",
      "dataAiHint": "testing travel",
      "baseCurrency": "INR",
      "ownerId": "WHEtiIf0OZdrfIfwN2yGc0B0ReE3",
      "createdAt": {
        "_seconds": 1750860089,
        "_nanoseconds": 100000000
      },
      "members": [
        "WHEtiIf0OZdrfIfwN2yGc0B0ReE3",
        "dGdKM1ywlCWYp8LfGL10SYOZfDa2",
        "Y1vT3UZ0pJVKYavxbKGSxt0Scr23",
        "WXKpibqH1idv1MHxFLVuc1mb29h1",
        "pMHCV5Ps6ASc3dmQJdi5o2ageUD2",
        "OFwktrmtGVaU7eOUVo2BEzgh1Ir2",
        "2KmSLWs2rzRAUf5gw8hub6ywW9x1",
        "h5uHIffYuzML5TW4r6Z3IRy0bC13"
      ]
    },
    "X6R6dNZZ8Bv4BhukDjZ2": {
      "name": "Anime Lover",
      "destination": "Kolkata",
      "startDate": {
        "_seconds": 1751567400,
        "_nanoseconds": 0
      },
      "endDate": {
        "_seconds": 1751999400,
        "_nanoseconds": 0
      },
      "description": "",
      "coverPhotoURL": "https://placehold.co/600x400.png?text=Anime%20Lover",
      "dataAiHint": "kolkata travel",
      "baseCurrency": "INR",
      "ownerId": "SjQAB1iM7xSaTqzJ0HiVc5uLjrq2",
      "createdAt": {
        "_seconds": 1751482413,
        "_nanoseconds": 35000000
      },
      "members": [
        "SjQAB1iM7xSaTqzJ0HiVc5uLjrq2",
        "HOS9cGUTEJZz49j27OU03TdAF6N2"
      ]
    },
    "d0lLXUNse6KQBjrnIjBp": {
      "name": "Friend",
      "destination": "darjeeling",
      "startDate": {
        "_seconds": 1747679400,
        "_nanoseconds": 0
      },
      "endDate": {
        "_seconds": 1748284200,
        "_nanoseconds": 0
      },
      "description": "",
      "coverPhotoURL": "https://placehold.co/600x400.png?text=Friend",
      "dataAiHint": "darjeeling travel",
      "ownerId": "dGdKM1ywlCWYp8LfGL10SYOZfDa2",
      "createdAt": {
        "_seconds": 1747566579,
        "_nanoseconds": 290000000
      },
      "members": [
        "dGdKM1ywlCWYp8LfGL10SYOZfDa2",
        "WHEtiIf0OZdrfIfwN2yGc0B0ReE3",
        "nFwfgL28iJT5nCDVPaPAHnya7jg2"
      ],
      "baseCurrency": "INR"
    },
    "dGhD9USLPpvnFjnR1m1q": {
      "name": "digha",
      "destination": "digha",
      "startDate": {
        "_seconds": 1748629800,
        "_nanoseconds": 0
      },
      "endDate": {
        "_seconds": 1748975400,
        "_nanoseconds": 0
      },
      "description": "",
      "coverPhotoURL": "https://placehold.co/600x400.png?text=digha",
      "dataAiHint": "digha travel",
      "baseCurrency": "INR",
      "ownerId": "dGdKM1ywlCWYp8LfGL10SYOZfDa2",
      "createdAt": {
        "_seconds": 1748686172,
        "_nanoseconds": 67000000
      },
      "members": [
        "dGdKM1ywlCWYp8LfGL10SYOZfDa2",
        "nFwfgL28iJT5nCDVPaPAHnya7jg2"
      ]
    },
    "eZHVz7q5jZYO9UkOisHl": {
      "name": "Darjeeling",
      "destination": "darjeeling",
      "startDate": {
        "_seconds": 1747679400,
        "_nanoseconds": 0
      },
      "endDate": {
        "_seconds": 1748284200,
        "_nanoseconds": 0
      },
      "description": "",
      "coverPhotoURL": "https://placehold.co/600x400.png?text=Darjeeling",
      "dataAiHint": "darjeeling travel",
      "baseCurrency": "INR",
      "ownerId": "WHEtiIf0OZdrfIfwN2yGc0B0ReE3",
      "members": [
        "WHEtiIf0OZdrfIfwN2yGc0B0ReE3"
      ],
      "createdAt": {
        "_seconds": 1747645068,
        "_nanoseconds": 942000000
      }
    },
    "nSM52LP2DLXe1MC6wvs4": {
      "name": "SWIZERLAND",
      "dataAiHint": "swizerland travel",
      "coverPhotoURL": "https://placehold.co/600x400.png?text=SWIZERLAND",
      "startDate": {
        "_seconds": 1752604200,
        "_nanoseconds": 0
      },
      "endDate": {
        "_seconds": 1753122600,
        "_nanoseconds": 0
      },
      "baseCurrency": "INR",
      "description": "Ami ghurte jabo",
      "ownerId": "dGdKM1ywlCWYp8LfGL10SYOZfDa2",
      "destination": "SWIZERLAND",
      "createdAt": {
        "_seconds": 1749926398,
        "_nanoseconds": 3000000
      },
      "members": [
        "dGdKM1ywlCWYp8LfGL10SYOZfDa2",
        "nFwfgL28iJT5nCDVPaPAHnya7jg2"
      ]
    },
    "vlwIaD4MPE5yHvywEzjP": {
      "name": "oottii",
      "destination": "ooty",
      "startDate": {
        "_seconds": 1747765800,
        "_nanoseconds": 0
      },
      "endDate": {
        "_seconds": 1748284200,
        "_nanoseconds": 0
      },
      "description": "",
      "coverPhotoURL": "https://placehold.co/600x400.png?text=oottii",
      "dataAiHint": "ooty travel",
      "ownerId": "dGdKM1ywlCWYp8LfGL10SYOZfDa2",
      "createdAt": {
        "_seconds": 1747567917,
        "_nanoseconds": 986000000
      },
      "members": [
        "dGdKM1ywlCWYp8LfGL10SYOZfDa2",
        "nFwfgL28iJT5nCDVPaPAHnya7jg2"
      ]
    },
    "zOC0qmc5XsD2uIvPcZfu": {
      "baseCurrency": "INR",
      "coverPhotoURL": "https://placehold.co/600x400.png?text=Moja",
      "ownerId": "2KmSLWs2rzRAUf5gw8hub6ywW9x1",
      "description": "Moja hobe khela hobe.",
      "startDate": {
        "_seconds": 1749753000,
        "_nanoseconds": 0
      },
      "dataAiHint": "kolkata travel",
      "endDate": {
        "_seconds": 1750012200,
        "_nanoseconds": 0
      },
      "name": "Moja",
      "destination": "Kolkata",
      "createdAt": {
        "_seconds": 1749234381,
        "_nanoseconds": 80000000
      },
      "members": [
        "2KmSLWs2rzRAUf5gw8hub6ywW9x1",
        "nFwfgL28iJT5nCDVPaPAHnya7jg2",
        "dGdKM1ywlCWYp8LfGL10SYOZfDa2"
      ]
    }
  },
  "users": {
    "0UvIfHXyRkNsyanC3gZyIfcH7s02": {
      "photoURL": "https://lh3.googleusercontent.com/a/ACg8ocKDqpoySHhyJZKAJUOqyrSbX2OZB3A-ZgRk4LNEQgMXk8Mb1qcg=s96-c",
      "uid": "0UvIfHXyRkNsyanC3gZyIfcH7s02",
      "createdAt": {
        "_seconds": 1750777349,
        "_nanoseconds": 357000000
      },
      "displayName": "Aditya Jyoti Kayal",
      "email": "adityakayal124@gmail.com",
      "lastLogin": {
        "_seconds": 1752035795,
        "_nanoseconds": 86000000
      }
    },
    "2KmSLWs2rzRAUf5gw8hub6ywW9x1": {
      "photoURL": "https://lh3.googleusercontent.com/a/ACg8ocJd4AlAksQYGv00lmzdtjbDEFBcLW897z9QWWLX21cUCqAML9o=s96-c",
      "uid": "2KmSLWs2rzRAUf5gw8hub6ywW9x1",
      "createdAt": {
        "_seconds": 1749234284,
        "_nanoseconds": 662000000
      },
      "displayName": "Pranay De",
      "email": "pranayde201@gmail.com",
      "lastLogin": {
        "_seconds": 1751646153,
        "_nanoseconds": 61000000
      }
    },
    "8gXk0K0IrldaCTvCkMRIcBSqkei1": {
      "photoURL": "https://lh3.googleusercontent.com/a/ACg8ocJtUgrjZLfJTVMYRNSXFHgazMNJDDZXDOeLu8n1xZEqgvZlpA=s96-c",
      "uid": "8gXk0K0IrldaCTvCkMRIcBSqkei1",
      "lastLogin": {
        "_seconds": 1750848229,
        "_nanoseconds": 45000000
      },
      "createdAt": {
        "_seconds": 1750848229,
        "_nanoseconds": 45000000
      },
      "displayName": "Rushali Ganguly",
      "email": "tanusriganguly3456@gmail.com"
    },
    "EswwiypXSlNvwyuhDRQl62r4jRF3": {
      "photoURL": "https://lh3.googleusercontent.com/a/ACg8ocJyF0-NepjJtl5EX0khMNC3UFcR01yheQFCNuZvBVSWRLnwIQ=s96-c",
      "uid": "EswwiypXSlNvwyuhDRQl62r4jRF3",
      "createdAt": {
        "_seconds": 1750777768,
        "_nanoseconds": 168000000
      },
      "displayName": "Debasree Bhattacharya",
      "email": "bhattacharyadebasree4@gmail.com",
      "lastLogin": {
        "_seconds": 1750778252,
        "_nanoseconds": 638000000
      }
    },
    "Fzdmgoj5LpYHAweyMfiFSPXghj22": {
      "photoURL": "https://lh3.googleusercontent.com/a-/ALV-UjVxlB3t7OWHgd-5RrPnUiQdGnzqZr5YG-BTPzzi6jC05NsQLJml6iGCIB1QNyz8DVAP4TZW-HXuIRUevOWBded8PyT3xeEGIuRDb-WKyLZE6NSEBlnkwIZn1h1eoVk-hiD7sc0XJkKNEo5GyYwZ7eUDGOwWrswNHvOj6HFr7eOCqJevVaIn11Atyw_lVMrG3POZxWKwcOZYRAW9cG7jHBFBc2QqvP7SLd5X6Q7NCGOgtG-lKv3WhURa_brmD5JR9CdejVKCEdw8h5NjYOOYkdWA0g_eaCTfF5n_T_LZNdLZjnLRaPQkKiMgkXHLlMvzjpHfYiEJe0vkbZZiXPe-0FDtiO9OS_Tn18Ufp1Wdp-8medS8MK7NSKGocBQ4ZT_E1OdON0U7DKPw6AsqG1veUy32lw0Yn1muAazzf06T18Tm-rD6q0hPAc2jd-anhtfheplhAkDM2QNarts_ivurE7f6ZTFTsmw3RUizoP0ljH748JqWLevT6PAUkZ8RyqLVaA_Yiyf92844IvN-woGDCoQC67V2fUjdLb_js7EtseyvL9BTLEwnr3WITvQhNWqLDQxSLK93hNLFN6Y8za2__YrKTrtzloVe8opTicOgtN6DqlMN0Irb-v_0HBF5YZlFMUeNh-e_mSzw-wCuqFAPrsZuswJ_xl4qUlnvfWYCEawLb5fqP-jUk_QFWrGbtCxkjzo81PALpKa2MMJ0cqMVBrU2jq2WvN2B7n7eIlN0zmxKIB44Zlta-B1eU0j-Gj56__7v1zyqMeWS6_6pLJ17u-LYdFNUwu6jS5z9lsD5CZpiA-Ikgp2HPMKUd4e1A1gVYwBcy1Cds_tOKlc40M3t-oVj7PEv-xBa2qNdBge4XOi7pIMUm9_zKsn40oK6lOgRpH7AqDXBZ2Xb1S3jPScOuOZ2YcnY3_iMEBuc9czqbenz2vRlJe9rMyf4gkLPbOiu4dZqKow01dqkgTjjSEQvq82Hri0kBef7=s96-c",
      "uid": "Fzdmgoj5LpYHAweyMfiFSPXghj22",
      "createdAt": {
        "_seconds": 1750470752,
        "_nanoseconds": 228000000
      },
      "displayName": "Srinjinee Mitra",
      "email": "mitrasrinjinee12@gmail.com",
      "lastLogin": {
        "_seconds": 1750678515,
        "_nanoseconds": 131000000
      }
    },
    "HOS9cGUTEJZz49j27OU03TdAF6N2": {
      "photoURL": "https://lh3.googleusercontent.com/a/ACg8ocIIBKqLlPpPskKrjs3k-fAEV-MshyAiCWBOm64LQZ1WTtAgvJE=s96-c",
      "uid": "HOS9cGUTEJZz49j27OU03TdAF6N2",
      "lastLogin": {
        "_seconds": 1751482460,
        "_nanoseconds": 655000000
      },
      "createdAt": {
        "_seconds": 1751482460,
        "_nanoseconds": 655000000
      },
      "displayName": "Pranay De",
      "email": "pranaydeofficial20@gmail.com"
    },
    "OFwktrmtGVaU7eOUVo2BEzgh1Ir2": {
      "photoURL": "https://lh3.googleusercontent.com/a/ACg8ocJXIaEmdIL6gB4IHsbGeaw7KfYv-DeEwaS0WPiARdByVAjiEw=s96-c",
      "uid": "OFwktrmtGVaU7eOUVo2BEzgh1Ir2",
      "createdAt": {
        "_seconds": 1750777426,
        "_nanoseconds": 29000000
      },
      "displayName": "Snehasish Ganguly",
      "email": "prodoshmitter2000@gmail.com",
      "lastLogin": {
        "_seconds": 1750777722,
        "_nanoseconds": 268000000
      }
    },
    "SjQAB1iM7xSaTqzJ0HiVc5uLjrq2": {
      "photoURL": "https://lh3.googleusercontent.com/a/ACg8ocLMhRpryxwNBl_q_ji-T2NDSul_D3EFB7v9s_Y1Ij31EwXoOX7x=s96-c",
      "uid": "SjQAB1iM7xSaTqzJ0HiVc5uLjrq2",
      "createdAt": {
        "_seconds": 1751482388,
        "_nanoseconds": 726000000
      },
      "displayName": "Pranay De",
      "email": "pranaydeyoyo@gmail.com",
      "lastLogin": {
        "_seconds": 1751482589,
        "_nanoseconds": 119000000
      }
    },
    "WHEtiIf0OZdrfIfwN2yGc0B0ReE3": {
      "photoURL": "https://lh3.googleusercontent.com/a/ACg8ocKRssPst7bN-KFngT58H0g9rW1E42mdyJpciRP3MA1GLcnb_b1D=s96-c",
      "uid": "WHEtiIf0OZdrfIfwN2yGc0B0ReE3",
      "displayName": "Amitava Datta",
      "email": "dattaamitava2004@gmail.com",
      "createdAt": {
        "_seconds": 1747676741,
        "_nanoseconds": 233000000
      },
      "lastLogin": {
        "_seconds": 1750941885,
        "_nanoseconds": 321000000
      }
    },
    "WXKpibqH1idv1MHxFLVuc1mb29h1": {
      "photoURL": "https://lh3.googleusercontent.com/a/ACg8ocI8HXq_-DU6vl19Y8SqDNsft15DWTszMNIVZkPlnkBB5q5ZdVo=s96-c",
      "uid": "WXKpibqH1idv1MHxFLVuc1mb29h1",
      "createdAt": {
        "_seconds": 1750860177,
        "_nanoseconds": 380000000
      },
      "displayName": "Dev Nexus",
      "email": "devnexus3@gmail.com",
      "lastLogin": {
        "_seconds": 1750874136,
        "_nanoseconds": 973000000
      }
    },
    "Y1vT3UZ0pJVKYavxbKGSxt0Scr23": {
      "photoURL": "https://lh3.googleusercontent.com/a/ACg8ocKsh45FTJt5ZvXrbJAt1mHxMoZhK--RD1P154Z693Jmv_5S=s96-c",
      "uid": "Y1vT3UZ0pJVKYavxbKGSxt0Scr23",
      "createdAt": {
        "_seconds": 1750859871,
        "_nanoseconds": 429000000
      },
      "displayName": "Utsav Unites",
      "email": "utsavunites@gmail.com",
      "lastLogin": {
        "_seconds": 1750874138,
        "_nanoseconds": 276000000
      }
    },
    "ZDif3dTZDmfNOcgvqFoVO1xEizi2": {
      "photoURL": "https://lh3.googleusercontent.com/a/ACg8ocIFgl-WyXaGJl97fW3hSBnmF-ezV4aQwpmpeDSpdMzlOPV60A=s96-c",
      "uid": "ZDif3dTZDmfNOcgvqFoVO1xEizi2",
      "createdAt": {
        "_seconds": 1750749886,
        "_nanoseconds": 124000000
      },
      "displayName": "Srinjinee Mitra",
      "email": "srinjineemitra@gmail.com",
      "lastLogin": {
        "_seconds": 1750750093,
        "_nanoseconds": 724000000
      }
    },
    "dGdKM1ywlCWYp8LfGL10SYOZfDa2": {
      "photoURL": "https://lh3.googleusercontent.com/a/ACg8ocJAj1EECIOn7aKFWNgyGeY_k_SBV7u5nS5zKqSLPU3pybbgYc4=s96-c",
      "uid": "dGdKM1ywlCWYp8LfGL10SYOZfDa2",
      "displayName": "AmitavaPranay",
      "email": "legendaryduo202327@gmail.com",
      "createdAt": {
        "_seconds": 1747676821,
        "_nanoseconds": 944000000
      },
      "lastLogin": {
        "_seconds": 1752140200,
        "_nanoseconds": 599000000
      }
    },
    "ejvuhdTDUaNlunDreHiw6DSfZzc2": {
      "photoURL": "https://lh3.googleusercontent.com/a/ACg8ocKdQ1S6fEzLKHr11DypuXtt8eTZMl6-qtZOOp_2StNE7hfroG36=s96-c",
      "uid": "ejvuhdTDUaNlunDreHiw6DSfZzc2",
      "createdAt": {
        "_seconds": 1750779444,
        "_nanoseconds": 868000000
      },
      "displayName": "Archisman Banerjee",
      "email": "archismanbanerjee13@gmail.com",
      "lastLogin": {
        "_seconds": 1753454343,
        "_nanoseconds": 437000000
      }
    },
    "h5uHIffYuzML5TW4r6Z3IRy0bC13": {
      "photoURL": "https://lh3.googleusercontent.com/a/ACg8ocLKqXTpg9eeHFzrwRsJfVaYJZ0HVqCKUs_oU3CsIdAAjkJeguWh=s96-c",
      "uid": "h5uHIffYuzML5TW4r6Z3IRy0bC13",
      "createdAt": {
        "_seconds": 1750776939,
        "_nanoseconds": 231000000
      },
      "displayName": "Aritra karmakar",
      "email": "aritra8.7.2005@gmail.com",
      "lastLogin": {
        "_seconds": 1752070858,
        "_nanoseconds": 45000000
      }
    },
    "nFwfgL28iJT5nCDVPaPAHnya7jg2": {
      "photoURL": "https://lh3.googleusercontent.com/a/ACg8ocLBIUxBxCc9v8cbrxlB5eHOvoy2dszi9Ih2AdBT6m7tfbUSQlst2w=s96-c",
      "uid": "nFwfgL28iJT5nCDVPaPAHnya7jg2",
      "createdAt": {
        "_seconds": 1747677812,
        "_nanoseconds": 254000000
      },
      "displayName": "Amitava Datta",
      "email": "dattaarup2004@gmail.com",
      "lastLogin": {
        "_seconds": 1752311618,
        "_nanoseconds": 444000000
      }
    },
    "pMHCV5Ps6ASc3dmQJdi5o2ageUD2": {
      "photoURL": "https://lh3.googleusercontent.com/a/ACg8ocL4zPFmfKYHI93kAfsFk-hzqQaHDj0lZJ3LUTqExuwOw4djAtT5=s96-c",
      "uid": "pMHCV5Ps6ASc3dmQJdi5o2ageUD2",
      "createdAt": {
        "_seconds": 1750611756,
        "_nanoseconds": 89000000
      },
      "displayName": "Rudraksh Ganguly",
      "email": "rganguly1705@gmail.com",
      "lastLogin": {
        "_seconds": 1751689073,
        "_nanoseconds": 644000000
      }
    },
    "qz8Mre992HZ2oZzS9fnvrGPZ4sz2": {
      "photoURL": "https://lh3.googleusercontent.com/a/ACg8ocIRwJuzMqGhakjPUl9vW4sIMUgGwEnUkOq5Typy0XVUuYrv9w=s96-c",
      "uid": "qz8Mre992HZ2oZzS9fnvrGPZ4sz2",
      "createdAt": {
        "_seconds": 1750484656,
        "_nanoseconds": 391000000
      },
      "displayName": "Shreya Paladhi",
      "email": "iamshreyapaladhi@gmail.com",
      "lastLogin": {
        "_seconds": 1750530345,
        "_nanoseconds": 79000000
      }
    }
  }
}